unrealircd_rpc_py/__init__.py
unrealircd_rpc_py/ConnectionFactory.py
unrealircd_rpc_py/connections/__init__.py
unrealircd_rpc_py/connections/live/__init__.py
unrealircd_rpc_py/connections/live/ILiveConnection.py
unrealircd_rpc_py/connections/live/live_http.py
unrealircd_rpc_py/connections/live/live_unixsocket.py
unrealircd_rpc_py/connections/sync/__init__.py
unrealircd_rpc_py/connections/sync/http.py
unrealircd_rpc_py/connections/sync/IConnection.py
unrealircd_rpc_py/connections/sync/unixsocket.py
unrealircd_rpc_py/exceptions/__init__.py
unrealircd_rpc_py/exceptions/rpc_exceptions.py
unrealircd_rpc_py/LiveConnectionFactory.py
unrealircd_rpc_py/modules/__init__.py
unrealircd_rpc_py/modules/tosql/__init__.py
unrealircd_rpc_py/modules/tosql/database.py
unrealircd_rpc_py/modules/tosql/models.py
unrealircd_rpc_py/modules/tosql/tosql.py
unrealircd_rpc_py/objects/__init__.py
unrealircd_rpc_py/objects/Channel.py
unrealircd_rpc_py/objects/Connthrottle.py
unrealircd_rpc_py/objects/Definition.py
unrealircd_rpc_py/objects/Log.py
unrealircd_rpc_py/objects/Message.py
unrealircd_rpc_py/objects/Name_ban.py
unrealircd_rpc_py/objects/Rpc.py
unrealircd_rpc_py/objects/Security_group.py
unrealircd_rpc_py/objects/Server.py
unrealircd_rpc_py/objects/Server_ban.py
unrealircd_rpc_py/objects/Server_ban_exeption.py
unrealircd_rpc_py/objects/Spamfilter.py
unrealircd_rpc_py/objects/Stats.py
unrealircd_rpc_py/objects/User.py
unrealircd_rpc_py/objects/Whowas.py
unrealircd_rpc_py/utils/__init__.py
unrealircd_rpc_py/utils/utils.py
unrealircd_rpc_py-3.1.6.dist-info/licenses/LICENSE
unrealircd_rpc_py-3.1.6.dist-info/METADATA
unrealircd_rpc_py-3.1.6.dist-info/WHEEL
unrealircd_rpc_py-3.1.6.dist-info/RECORD
