Metadata-Version: 2.4
Name: unrealircd-rpc-py
Version: 3.1.6
Summary: Python library for UnrealIRCd json-rpc
License-Expression: MIT
License-File: LICENSE
Keywords: Unrealircd,irc,jsonrpc,json-rpc,ircd
Author: adator
Author-email: adator@octobyte.ovh
Requires-Python: >=3.10
Classifier: Development Status :: 5 - Production/Stable
Classifier: Programming Language :: Python :: 3.10
Classifier: Operating System :: OS Independent
Requires-Dist: psycopg2-binary (>=2.9.11,<3.0.0)
Requires-Dist: pymysql (>=1.1.2,<2.0.0)
Requires-Dist: requests (>=2.32.5,<3.0.0)
Requires-Dist: sqlalchemy (>=2.0.46,<3.0.0)
Requires-Dist: websockets (>=13.1,<=16.0.0)
Project-URL: Homepage, https://octobyte.ovh/
Project-URL: Repository, https://github.com/adator85/unrealircd_rpc_py
